soundcloud/__init__.py
soundcloud/client.py
soundcloud/hashconversions.py
soundcloud/request.py
soundcloud/resource.py
soundcloud/tests/__init__.py
soundcloud/tests/test_client.py
soundcloud/tests/test_encoding.py
soundcloud/tests/test_oauth.py
soundcloud/tests/test_requests.py
soundcloud/tests/test_resource.py
soundcloud/tests/utils.py
soundcloud-0.4.2.dist-info/DESCRIPTION.rst
soundcloud-0.4.2.dist-info/METADATA
soundcloud-0.4.2.dist-info/RECORD
soundcloud-0.4.2.dist-info/WHEEL
soundcloud-0.4.2.dist-info/metadata.json
soundcloud-0.4.2.dist-info/top_level.txt
