Metadata-Version: 2.0
Name: soundcloud
Version: 0.4.2
Summary: A friendly wrapper library for the Soundcloud API
Home-page: https://github.com/soundcloud/soundcloud-python
Author: SoundCloud
Author-email: api@soundcloud.com
License: BSD
Platform: UNKNOWN
Classifier: Development Status :: 4 - Beta
Classifier: Intended Audience :: Developers
Classifier: License :: OSI Approved :: BSD License
Classifier: Operating System :: OS Independent
Classifier: Programming Language :: Python
Classifier: Topic :: Internet
Classifier: Topic :: Multimedia :: Sound/Audio
Classifier: Topic :: Software Development :: Libraries :: Python Modules
Requires-Dist: fudge (>=1.0.3)
Requires-Dist: requests (>=0.14.0)
Requires-Dist: simplejson (>=2.0)
